roml/__init__.py
roml/__version__.py
roml-0.0.1.dist-info/LICENSE
roml-0.0.1.dist-info/METADATA
roml-0.0.1.dist-info/WHEEL
roml-0.0.1.dist-info/top_level.txt
roml-0.0.1.dist-info/RECORD
